CHANGELOG.md
hwid/__init__.py
hwid/__main__.py
hwid/core.py
hwid/exceptions.py
hwid/main.py
hwid-0.1.0.dist-info/LICENSE
hwid-0.1.0.dist-info/METADATA
hwid-0.1.0.dist-info/WHEEL
hwid-0.1.0.dist-info/entry_points.txt
hwid-0.1.0.dist-info/RECORD
