Metadata-Version: 2.1
Name: hwid
Version: 0.1.0
Summary: Extract the `hwid` on Windows, Linux, Mac. Cross-platform using Python, native OS detection.
License: MIT
Keywords: hwid,hardware,id,unique,identifier,machine,fingerprint,fingerprinting,licensing,license,licensing,identification,machine
Author: hasansezertasan
Author-email: hasansezertasan@gmail.com
Maintainer: hasansezertasan
Maintainer-email: hasansezertasan@gmail.com
Requires-Python: >=3.0,<4.0
Classifier: Development Status :: 5 - Production/Stable
Classifier: Environment :: Console
Classifier: Intended Audience :: Developers
Classifier: License :: OSI Approved :: MIT License
Classifier: Operating System :: OS Independent
Classifier: Programming Language :: Python
Classifier: Programming Language :: Python :: 3
Classifier: Programming Language :: Python :: 3.4
Classifier: Programming Language :: Python :: 3.5
Classifier: Programming Language :: Python :: 3.6
Classifier: Programming Language :: Python :: 3.7
Classifier: Programming Language :: Python :: 3.8
Classifier: Programming Language :: Python :: 3.9
Classifier: Programming Language :: Python :: 3.10
Classifier: Programming Language :: Python :: 3.11
Classifier: Programming Language :: Python :: 3 :: Only
Classifier: Topic :: Software Development :: Libraries :: Python Modules
Project-URL: documentation, https://hasansezertasan.github.io/hwid/
Project-URL: homepage, https://github.com/hasansezertasan/hwid
Project-URL: repository, https://github.com/hasansezertasan/hwid
